x2case/__init__.py
x2case/com.py
x2case/const.py
x2case/func.py
x2case/jira.py
x2case/parser.py
x2case-1.2.3.dist-info/licenses/LICENSE
x2case-1.2.3.dist-info/METADATA
x2case-1.2.3.dist-info/WHEEL
x2case-1.2.3.dist-info/top_level.txt
x2case-1.2.3.dist-info/RECORD
