Metadata-Version: 2.4
Name: x2case
Version: 1.2.3
Summary: Xmind to jira test case
Author-email: Zeno Zhang <z_ok@me.com>
License: MIT
Project-URL: Homepage, https://github.com/Allenzzz/x2case
Project-URL: Repository, https://github.com/Allenzzz/x2case
Keywords: Xmind,testcase,jira,xmindparser
Classifier: Programming Language :: Python :: 3
Classifier: License :: OSI Approved :: MIT License
Classifier: Operating System :: OS Independent
Requires-Python: >=3.11
License-File: LICENSE
Requires-Dist: xmindparser>=1.0.0
Provides-Extra: dev
Requires-Dist: pytest; extra == "dev"
Requires-Dist: pytest-cov; extra == "dev"
Requires-Dist: black; extra == "dev"
Requires-Dist: flake8; extra == "dev"
Dynamic: license-file
